pysimplelogger/__init__.py
pysimplelogger/logger3.py
pysimplelogger-0.1.5.dist-info/LICENSE
pysimplelogger-0.1.5.dist-info/WHEEL
pysimplelogger-0.1.5.dist-info/METADATA
pysimplelogger-0.1.5.dist-info/RECORD
